{"metadata":{},"options":{"plugins":[{"key":"base$0$0","visitor":{"Program":{"enter":[null]},"_exploded":true,"_verified":true},"options":{"generateLetDeclarations":true,"enforceStrictMode":false}},{"key":"transform-meteor-dynamic-import","visitor":{"_exploded":{},"_verified":{},"CallExpression":{"enter":[null]}},"options":{}},{"key":"base$0$2","visitor":{"CallExpression":{"enter":[null]},"BinaryExpression":{"enter":[null]},"MemberExpression":{"enter":[null],"exit":[null]},"_exploded":true,"_verified":true,"Identifier":{"enter":[null]},"JSXIdentifier":{"enter":[null]}},"options":{}},{"key":"base$0$3","visitor":{"_exploded":{},"_verified":{},"PrivateName":{"enter":[null]},"ClassDeclaration":{"enter":[null]},"ClassExpression":{"enter":[null]}},"options":{"loose":true}},{"key":"base$0$4","visitor":{"Program":{"exit":[null]},"_exploded":true,"_verified":true},"options":{"allowTopLevelThis":true,"strictMode":false,"loose":true}},{"key":"base$0$1$0","visitor":{"_exploded":{},"_verified":{},"JSXNamespacedName":{"enter":[null]},"JSXElement":{"exit":[null]},"JSXFragment":{"exit":[null]},"Program":{"enter":[null],"exit":[null]},"JSXAttribute":{"enter":[null]}},"options":{"pragma":"React.createElement","pragmaFrag":"React.Fragment","throwIfNamespace":true,"useBuiltIns":false}},{"key":"base$0$1$1","visitor":{"ExportDefaultDeclaration":{"enter":[null]},"CallExpression":{"enter":[null]},"_exploded":true,"_verified":true},"options":{}},{"key":"base$0$0$0","visitor":{"_exploded":true,"_verified":true},"options":{}},{"key":"base$0$0$1","visitor":{"_exploded":true,"_verified":true},"options":{}},{"key":"base$0$0$2","visitor":{"_exploded":true,"_verified":true},"options":{}},{"key":"base$0$0$3","visitor":{"ForOfStatement":{"enter":[null]},"_exploded":true,"_verified":true},"options":{"loose":true}},{"key":"base$0$0$4","visitor":{"NumericLiteral":{"enter":[null]},"StringLiteral":{"enter":[null]},"_exploded":true,"_verified":true},"options":{}},{"key":"base$0$0$5","visitor":{"TaggedTemplateExpression":{"enter":[null]},"TemplateLiteral":{"enter":[null]},"_exploded":true,"_verified":true},"options":{}},{"key":"base$0$0$6","visitor":{"_exploded":true,"_verified":true,"FunctionDeclaration":{"enter":[null]},"FunctionExpression":{"enter":[null]},"ObjectMethod":{"enter":[null]},"ArrowFunctionExpression":{"enter":[null]},"ClassMethod":{"enter":[null]}},"options":{}},{"key":"base$0$0$7","visitor":{"_exploded":{},"_verified":{},"VariableDeclarator":{"enter":[null]},"ExportNamedDeclaration":{"enter":[null]},"CatchClause":{"enter":[null]},"AssignmentExpression":{"enter":[null]},"ObjectExpression":{"enter":[null]},"FunctionDeclaration":{"enter":[null]},"FunctionExpression":{"enter":[null]},"ObjectMethod":{"enter":[null]},"ArrowFunctionExpression":{"enter":[null]},"ClassMethod":{"enter":[null]},"ForInStatement":{"enter":[null]},"ForOfStatement":{"enter":[null]}},"options":{}},{"key":"base$0$0$8","visitor":{"_exploded":{},"_verified":{},"Program":{"enter":[null]},"ImportDeclaration":{"enter":[null,null]},"ClassProperty":{"enter":[null]},"ClassPrivateProperty":{"enter":[null]},"AssignmentPattern":{"enter":[null]},"TypeCastExpression":{"enter":[null,null]},"CallExpression":{"enter":[null]},"OptionalCallExpression":{"enter":[null]},"NewExpression":{"enter":[null]},"ImportSpecifier":{"enter":[null]},"ClassDeclaration":{"enter":[null]},"ClassExpression":{"enter":[null]},"FunctionDeclaration":{"enter":[null]},"FunctionExpression":{"enter":[null]},"ObjectMethod":{"enter":[null]},"ArrowFunctionExpression":{"enter":[null]},"ClassMethod":{"enter":[null]},"AnyTypeAnnotation":{"enter":[null]},"ArrayTypeAnnotation":{"enter":[null]},"BooleanTypeAnnotation":{"enter":[null]},"BooleanLiteralTypeAnnotation":{"enter":[null]},"NullLiteralTypeAnnotation":{"enter":[null]},"ClassImplements":{"enter":[null]},"DeclareClass":{"enter":[null]},"DeclareFunction":{"enter":[null]},"DeclareInterface":{"enter":[null]},"DeclareModule":{"enter":[null]},"DeclareModuleExports":{"enter":[null]},"DeclareTypeAlias":{"enter":[null]},"DeclareOpaqueType":{"enter":[null]},"DeclareVariable":{"enter":[null]},"DeclareExportDeclaration":{"enter":[null]},"DeclareExportAllDeclaration":{"enter":[null]},"DeclaredPredicate":{"enter":[null]},"ExistsTypeAnnotation":{"enter":[null]},"FunctionTypeAnnotation":{"enter":[null]},"FunctionTypeParam":{"enter":[null]},"GenericTypeAnnotation":{"enter":[null]},"InferredPredicate":{"enter":[null]},"InterfaceExtends":{"enter":[null]},"InterfaceDeclaration":{"enter":[null]},"InterfaceTypeAnnotation":{"enter":[null]},"IntersectionTypeAnnotation":{"enter":[null]},"MixedTypeAnnotation":{"enter":[null]},"EmptyTypeAnnotation":{"enter":[null]},"NullableTypeAnnotation":{"enter":[null]},"NumberLiteralTypeAnnotation":{"enter":[null]},"NumberTypeAnnotation":{"enter":[null]},"ObjectTypeAnnotation":{"enter":[null]},"ObjectTypeInternalSlot":{"enter":[null]},"ObjectTypeCallProperty":{"enter":[null]},"ObjectTypeIndexer":{"enter":[null]},"ObjectTypeProperty":{"enter":[null]},"ObjectTypeSpreadProperty":{"enter":[null]},"OpaqueType":{"enter":[null]},"QualifiedTypeIdentifier":{"enter":[null]},"StringLiteralTypeAnnotation":{"enter":[null]},"StringTypeAnnotation":{"enter":[null]},"ThisTypeAnnotation":{"enter":[null]},"TupleTypeAnnotation":{"enter":[null]},"TypeofTypeAnnotation":{"enter":[null]},"TypeAlias":{"enter":[null]},"TypeAnnotation":{"enter":[null]},"TypeParameter":{"enter":[null]},"TypeParameterDeclaration":{"enter":[null]},"TypeParameterInstantiation":{"enter":[null]},"UnionTypeAnnotation":{"enter":[null]},"Variance":{"enter":[null]},"VoidTypeAnnotation":{"enter":[null]},"ExportAllDeclaration":{"enter":[null]},"ExportDefaultDeclaration":{"enter":[null]},"ExportNamedDeclaration":{"enter":[null]}},"options":{}},{"key":"base$0$0$9","visitor":{"AssignmentExpression":{"enter":[null]},"BinaryExpression":{"enter":[null]},"_exploded":true,"_verified":true},"options":{}},{"key":"base$0$0$10","visitor":{"_exploded":{},"_verified":{},"Program":{"enter":[null]}},"options":{}}],"presets":[],"compact":false,"sourceMaps":true,"ast":true,"babelrc":false,"configFile":false,"parserOpts":{"sourceType":"module","sourceFileName":"/home/siddharth/Desktop/amar/My_Utopia/imports/startup/client/route.js","plugins":["*","flow","jsx","asyncGenerators","bigInt","classPrivateMethods","classPrivateProperties","classProperties","doExpressions","dynamicImport","exportDefaultFrom","exportExtensions","exportNamespaceFrom","functionBind","functionSent","importMeta","nullishCoalescingOperator","numericSeparator","objectRestSpread","optionalCatchBinding","optionalChaining",["pipelineOperator",{"proposal":"minimal"}],"throwExpressions","dynamicImport","classProperties","classPrivateProperties","jsx",["flow",{}],"asyncGenerators","objectRestSpread","objectRestSpread",["flow",{}],"asyncGenerators"],"allowImportExportEverywhere":true,"allowReturnOutsideFunction":true,"strictMode":false},"caller":{"name":"meteor","arch":"web.browser"},"sourceFileName":"imports/startup/client/route.js","filename":"/home/siddharth/Desktop/amar/My_Utopia/imports/startup/client/route.js","passPerPreset":false,"envName":"development","cwd":"/home/siddharth/Desktop/amar/My_Utopia","root":"/home/siddharth/Desktop/amar/My_Utopia","generatorOpts":{"filename":"/home/siddharth/Desktop/amar/My_Utopia/imports/startup/client/route.js","comments":true,"compact":false,"sourceMaps":true,"sourceFileName":"imports/startup/client/route.js"}},"code":"let FlowRouter;\nmodule.link(\"meteor/kadira:flow-router\", {\n  FlowRouter(v) {\n    FlowRouter = v;\n  }\n\n}, 0);\nlet BlazeLayout;\nmodule.link(\"meteor/kadira:blaze-layout\", {\n  BlazeLayout(v) {\n    BlazeLayout = v;\n  }\n\n}, 1);\nmodule.link(\"../../ui/pages/main/welocomePage.js\");\nmodule.link(\"../../ui/pages/main/identity-reg.js\");\nmodule.link(\"../../ui/layouts/body/body.js\");\nFlowRouter.route('/', {\n  name: 'welocomePage',\n\n  action() {\n    BlazeLayout.render('App_body', {\n      main: 'welocomePage'\n    });\n  }\n\n});\nFlowRouter.route('/identity-reg', {\n  name: 'identity-reg',\n\n  action() {\n    BlazeLayout.render('App_body', {\n      main: 'identity-reg'\n    });\n  }\n\n});","map":{"version":3,"sources":["imports/startup/client/route.js"],"names":["FlowRouter","module","link","v","BlazeLayout","route","name","action","render","main"],"mappings":"AAAA,IAAIA,UAAJ;AAAeC,MAAM,CAACC,IAAP,CAAY,2BAAZ,EAAwC;AAACF,EAAAA,UAAU,CAACG,CAAD,EAAG;AAACH,IAAAA,UAAU,GAACG,CAAX;AAAa;;AAA5B,CAAxC,EAAsE,CAAtE;AAAyE,IAAIC,WAAJ;AAAgBH,MAAM,CAACC,IAAP,CAAY,4BAAZ,EAAyC;AAACE,EAAAA,WAAW,CAACD,CAAD,EAAG;AAACC,IAAAA,WAAW,GAACD,CAAZ;AAAc;;AAA9B,CAAzC,EAAyE,CAAzE;AAA4EF,MAAM,CAACC,IAAP,CAAY,qCAAZ;AAAmDD,MAAM,CAACC,IAAP,CAAY,qCAAZ;AAAmDD,MAAM,CAACC,IAAP,CAAY,+BAAZ;AAO1RF,UAAU,CAACK,KAAX,CAAiB,GAAjB,EAAsB;AACpBC,EAAAA,IAAI,EAAE,cADc;;AAEpBC,EAAAA,MAAM,GAAG;AACPH,IAAAA,WAAW,CAACI,MAAZ,CAAmB,UAAnB,EAA+B;AAAEC,MAAAA,IAAI,EAAE;AAAR,KAA/B;AACD;;AAJmB,CAAtB;AAQAT,UAAU,CAACK,KAAX,CAAiB,eAAjB,EAAkC;AAChCC,EAAAA,IAAI,EAAE,cAD0B;;AAEhCC,EAAAA,MAAM,GAAG;AACPH,IAAAA,WAAW,CAACI,MAAZ,CAAmB,UAAnB,EAA+B;AAAEC,MAAAA,IAAI,EAAE;AAAR,KAA/B;AACD;;AAJ+B,CAAlC","sourcesContent":["import { FlowRouter } from 'meteor/kadira:flow-router';\nimport { BlazeLayout } from 'meteor/kadira:blaze-layout';\n\nimport \"../../ui/pages/main/welocomePage.js\";\nimport \"../../ui/pages/main/identity-reg.js\";\nimport \"../../ui/layouts/body/body.js\"\n\nFlowRouter.route('/', {\n  name: 'welocomePage',\n  action() {\n    BlazeLayout.render('App_body', { main: 'welocomePage' });\n  },\n});\n\n\nFlowRouter.route('/identity-reg', {\n  name: 'identity-reg',\n  action() {\n    BlazeLayout.render('App_body', { main: 'identity-reg' });\n  },\n});\n"]},"sourceType":"script","hash":"faca1b750a6a3975632f1162de077e0ca7cc2a78"}
